setup.py
flexicon/__init__.py
flexicon.egg-info/PKG-INFO
flexicon.egg-info/SOURCES.txt
flexicon.egg-info/dependency_links.txt
flexicon.egg-info/requires.txt
flexicon.egg-info/top_level.txt