Metadata-Version: 1.1
Name: flexicon
Version: 0.1.0
Summary: A lightweight regex-based lexing framework
Home-page: https://github.com/bitlang/flexicon
Author: Josh Junon
Author-email: josh@junon.me
License: UNKNOWN
Download-URL: https://github.com/bitlang/flexicon/archive/0.1.0.tar.gz
Keywords: lexer,lexing,tokenizer,regex,parsing,ast
Platform: UNKNOWN
